SmartModels/SmartModelCNN.py
SmartModels/VisionModel.py
SmartModels/__init__.py
SmartModels/utils.py
sodalmodel-0.1.2.dist-info/METADATA
sodalmodel-0.1.2.dist-info/WHEEL
sodalmodel-0.1.2.dist-info/top_level.txt
sodalmodel-0.1.2.dist-info/RECORD
