Metadata-Version: 2.4
Name: SODALMODEL
Version: 0.1.2
Summary: SODAL (Secure Object Detection and Auto-Labeling Framework): A simple yet powerful CNN wrapper for object detection, auto-labeling, training, evaluation, and model security with password protection.
Home-page: https://github.com/YKandoloJean/SMARTVISIONCNN
Author: Yotcheb Kandolo Jean
Author-email: kandoloyotchebjean@gmail.com
License: MIT
Classifier: Programming Language :: Python :: 3
Classifier: License :: OSI Approved :: MIT License
Classifier: Operating System :: OS Independent
Classifier: Topic :: Scientific/Engineering :: Artificial Intelligence
Classifier: Intended Audience :: Developers
Requires-Python: >=3.7
Requires-Dist: tensorflow>=2.0
Requires-Dist: matplotlib
Requires-Dist: scikit-learn
Requires-Dist: opencv-python
Requires-Dist: tensorflow-hub
Requires-Dist: ultralytics
Requires-Dist: numpy
Dynamic: author
Dynamic: author-email
Dynamic: classifier
Dynamic: description
Dynamic: description-content-type
Dynamic: home-page
Dynamic: license
Dynamic: requires-dist
Dynamic: requires-python
Dynamic: summary
